jloader/__init__.py
jloader/jloader.py
jloader-0.0.7.dist-info/LICENSE
jloader-0.0.7.dist-info/METADATA
jloader-0.0.7.dist-info/WHEEL
jloader-0.0.7.dist-info/top_level.txt
jloader-0.0.7.dist-info/RECORD
