Metadata-Version: 2.1
Name: jloader
Version: 0.0.7
Summary: Downloader for jupyter
Home-page: https://github.com/Lojaleto/jloader
Author: Lojaleto
Author-email: lojaleto@yandex.ru
Classifier: Programming Language :: Python :: 3.11
Classifier: License :: OSI Approved :: MIT License
Classifier: Operating System :: OS Independent
Requires-Python: >=3.6
License-File: LICENSE
Requires-Dist: requests (>=2.31.0)
